mba/VERSION
mba/__init__.py
mba/association.py
mba/config.yml
mba/mba.py
mba/config/__init__.py
mba/config/core.py
mba/data/__init__.py
mba/data/data_management.py
mba/data/make_dataset.py
mba/models/__init__.py
mba/models/predict_model.py
mba/models/train_model.py
mba/processing/__init__.py
mba/processing/association_features.py
mba/processing/build_features.py
mba/processing/plot_features.py
mba/visualization/__init__.py
mba/visualization/inventory.py
mba/visualization/sales.py
mba-1.0.0.dist-info/AUTHORS.rst
mba-1.0.0.dist-info/LICENSE
mba-1.0.0.dist-info/METADATA
mba-1.0.0.dist-info/WHEEL
mba-1.0.0.dist-info/top_level.txt
mba-1.0.0.dist-info/RECORD
