Metadata-Version: 2.1
Name: mba
Version: 1.0.0
Summary: Market Basket Analysis.
Home-page: https://github.com/HassanRady/mba
Author: Hassan Rady
Author-email: hassan.khaled.rady@gmail.com
License: MIT license
Keywords: mba
Platform: UNKNOWN
Classifier: Development Status :: 2 - Pre-Alpha
Classifier: Intended Audience :: Developers
Classifier: License :: OSI Approved :: MIT License
Classifier: Natural Language :: English
Classifier: Programming Language :: Python :: 3
Classifier: Programming Language :: Python :: 3.6
Classifier: Programming Language :: Python :: 3.7
Classifier: Programming Language :: Python :: 3.8
Requires-Python: >=3.6.0
License-File: LICENSE
License-File: AUTHORS.rst
Requires-Dist: scipy
Requires-Dist: bump2version
Requires-Dist: wheel
Requires-Dist: watchdog
Requires-Dist: flake8
Requires-Dist: tox (==3.14.0)
Requires-Dist: coverage (==4.5.4)
Requires-Dist: Sphinx (==1.8.5)
Requires-Dist: twine (==1.14.0)
Requires-Dist: build
Requires-Dist: pytest (==6.2.4)
Requires-Dist: pydantic
Requires-Dist: strictyaml
Requires-Dist: plotly
Requires-Dist: pandas
Requires-Dist: joblib
Requires-Dist: kaleido
Requires-Dist: SQLAlchemy
Requires-Dist: pymysql
Requires-Dist: mlxtend
